[1,["2aFS406yRKp6Ub1dM0yxH7","22Qrk3OflNYLRoBMiXIm9/","d83wEbXEJPF6H4pS1zNe7c","66SLQyE4pBPYdDn7KZzOtm","d44YMk8XRFL6Ii3ZXDoa2X","6esDbYPbtFPbIfxtPbvL2y","23QO9Ctv1Cx489/LSiCQrp","c9KOtY0YxMKYwJUhpnBm2l"],["_textureSetter"],["cc.SpriteFrame"],0,[[[{"name":"btn_f4_a","rect":[0,0,78,78],"offset":[0,0],"originalSize":[78,78],"capInsets":[0,0,0,0]}],[0],0,[0],[0],[0]],[[{"name":"btn_f2","rect":[0,0,78,78],"offset":[0,0],"originalSize":[78,78],"capInsets":[0,0,0,0]}],[0],0,[0],[0],[1]],[[{"name":"btn_f3","rect":[0,0,78,78],"offset":[0,0],"originalSize":[78,78],"capInsets":[0,0,0,0]}],[0],0,[0],[0],[2]],[[{"name":"btn_f4","rect":[0,0,78,78],"offset":[0,0],"originalSize":[78,78],"capInsets":[0,0,0,0]}],[0],0,[0],[0],[3]],[[{"name":"btn_f1","rect":[0,0,78,78],"offset":[0,0],"originalSize":[78,78],"capInsets":[0,0,0,0]}],[0],0,[0],[0],[4]],[[{"name":"btn_f2_a","rect":[0,0,78,78],"offset":[0,0],"originalSize":[78,78],"capInsets":[0,0,0,0]}],[0],0,[0],[0],[5]],[[{"name":"btn_f1_a","rect":[0,0,78,78],"offset":[0,0],"originalSize":[78,78],"capInsets":[0,0,0,0]}],[0],0,[0],[0],[6]],[[{"name":"btn_f3_a","rect":[0,0,78,78],"offset":[0,0],"originalSize":[78,78],"capInsets":[0,0,0,0]}],[0],0,[0],[0],[7]]]]